dualkey/__init__.py
dualkey/main.py
dualkey-1.1.2.dist-info/LICENSE
dualkey-1.1.2.dist-info/METADATA
dualkey-1.1.2.dist-info/WHEEL
dualkey-1.1.2.dist-info/entry_points.txt
dualkey-1.1.2.dist-info/top_level.txt
dualkey-1.1.2.dist-info/RECORD
