Metadata-Version: 2.1
Name: dualkey
Version: 1.1.2
Summary: Encryption/decryption tool
Home-page: https://github.com/ilovespectra/dual.key
Author: Tanner McMullen
License: MIT
Classifier: Programming Language :: Python :: 3
Classifier: License :: OSI Approved :: MIT License
Classifier: Operating System :: OS Independent
License-File: LICENSE
